{
  "httpMethod": "POST",
  "path": "/campanhas/trigger",
  "body": "{\"nome\":\"Black Friday 2024 - Sistema de Logística\",\"assunto\":\"🔥 Black Friday - Até 50% OFF em entregas!\",\"conteudo\":\"Não perca a maior promoção do ano! Descontos imperdíveis em todos os nossos serviços de logística. Aproveite frete grátis e entrega expressa com preços especiais. Válido apenas hoje!\",\"grupos\":[{\"tipo\":\"premium\",\"clientes\":[{\"id\":\"1\",\"nome\":\"Ari Henrique\",\"email\":\"arihenriquedev@hotmail.com\",\"regiao\":\"sudeste\"}]},{\"tipo\":\"geral\",\"clientes\":[{\"id\":\"2\",\"nome\":\"Estudante PUC\",\"email\":\"1457902@sga.pucminas.br\",\"regiao\":\"sudeste\"}]}]}"
}